LICENSE
README.md
setup.py
hypered/__init__.py
hypered/cli.py
hypered/dash.py
hypered.egg-info/PKG-INFO
hypered.egg-info/SOURCES.txt
hypered.egg-info/dependency_links.txt
hypered.egg-info/entry_points.txt
hypered.egg-info/requires.txt
hypered.egg-info/top_level.txt
hypered/interface/__init__.py
hypered/interface/misc.py
hypered/interface/objective.py
hypered/interface/optimize.py
hypered/interface/registry.py
hypered/interface/variable.py
hypered/optim/__init__.py
hypered/optim/aquisition_fn.py
hypered/optim/bayesian_optimization.py
hypered/optim/gaussian_process.py
hypered/optim/kernel.py
hypered/optim/space.py
hypered/server/__init__.py
hypered/server/experiment_loader.py
hypered/templates/index.html
hypered/utils/__init__.py
hypered/utils/dict_utils.py
tests/test_gaussian_process.py
tests/test_kernel.py