Metadata-Version: 2.1
Name: hypered
Version: 1.0.7
Summary: Simple hyper parameter tuning model.
Home-page: https://github.com/vahidk/hypered
Author: Vahid Kazemi
Author-email: vkazemi@gmail.com
License: MIT
License-File: LICENSE
Requires-Dist: scikit-optimize
Requires-Dist: flask
